koconf/__init__.py
koconf/cli.py
koconf/common.py
koconf/db.py
koconf/task.py
test/__init__.py
test/test_cli.py
test/test_common.py
test/test_db.py
test/test_task.py
koconf-0.2.1.dist-info/LICENSE
koconf-0.2.1.dist-info/METADATA
koconf-0.2.1.dist-info/WHEEL
koconf-0.2.1.dist-info/entry_points.txt
koconf-0.2.1.dist-info/top_level.txt
koconf-0.2.1.dist-info/RECORD
